[
  {
    "Date": "Dec 31, 2015",
    "Price": 430,
    "Open": 427.1,
    "High": 433.1,
    "Low": 417.1,
    "Vol.": "65.21K",
    "Change %": "0.66%"
  },
  {
    "Date": "Dec 30, 2015",
    "Price": 427.1,
    "Open": 431.9,
    "High": 435,
    "Low": 420.8,
    "Vol.": "68.27K",
    "Change %": "-1.10%"
  },
  {
    "Date": "Dec 29, 2015",
    "Price": 431.9,
    "Open": 421.8,
    "High": 433.6,
    "Low": 419.3,
    "Vol.": "70.65K",
    "Change %": "2.41%"
  },
  {
    "Date": "Dec 28, 2015",
    "Price": 421.8,
    "Open": 422.4,
    "High": 429.9,
    "Low": 417.1,
    "Vol.": "68.35K",
    "Change %": "-0.15%"
  },
  {
    "Date": "Dec 27, 2015",
    "Price": 422.4,
    "Open": 415.4,
    "High": 425.5,
    "Low": 406.1,
    "Vol.": "67.58K",
    "Change %": "1.69%"
  },
  {
    "Date": "Dec 26, 2015",
    "Price": 415.4,
    "Open": 454,
    "High": 456.5,
    "Low": 400.5,
    "Vol.": "208.58K",
    "Change %": "-8.52%"
  },
  {
    "Date": "Dec 25, 2015",
    "Price": 454,
    "Open": 453,
    "High": 457.4,
    "Low": 449.5,
    "Vol.": "42.39K",
    "Change %": "0.24%"
  },
  {
    "Date": "Dec 24, 2015",
    "Price": 453,
    "Open": 442.4,
    "High": 460.6,
    "Low": 441.8,
    "Vol.": "79.60K",
    "Change %": "2.38%"
  },
  {
    "Date": "Dec 23, 2015",
    "Price": 442.4,
    "Open": 437,
    "High": 444.8,
    "Low": 434.3,
    "Vol.": "63.25K",
    "Change %": "1.24%"
  },
  {
    "Date": "Dec 22, 2015",
    "Price": 437,
    "Open": 437.6,
    "High": 443.2,
    "Low": 433.3,
    "Vol.": "65.79K",
    "Change %": "-0.13%"
  },
  {
    "Date": "Dec 21, 2015",
    "Price": 437.6,
    "Open": 441.8,
    "High": 445.5,
    "Low": 424,
    "Vol.": "121.99K",
    "Change %": "-0.95%"
  },
  {
    "Date": "Dec 20, 2015",
    "Price": 441.8,
    "Open": 461.2,
    "High": 462.8,
    "Low": 431.1,
    "Vol.": "121.53K",
    "Change %": "-4.21%"
  },
  {
    "Date": "Dec 19, 2015",
    "Price": 461.2,
    "Open": 463.2,
    "High": 466,
    "Low": 452.3,
    "Vol.": "61.31K",
    "Change %": "-0.43%"
  },
  {
    "Date": "Dec 18, 2015",
    "Price": 463.2,
    "Open": 455.5,
    "High": 466.1,
    "Low": 453.5,
    "Vol.": "83.41K",
    "Change %": "1.68%"
  },
  {
    "Date": "Dec 17, 2015",
    "Price": 455.5,
    "Open": 454,
    "High": 458.4,
    "Low": 447.3,
    "Vol.": "64.58K",
    "Change %": "0.34%"
  },
  {
    "Date": "Dec 16, 2015",
    "Price": 454,
    "Open": 462.6,
    "High": 465.2,
    "Low": 437.4,
    "Vol.": "185.22K",
    "Change %": "-1.87%"
  },
  {
    "Date": "Dec 15, 2015",
    "Price": 462.6,
    "Open": 442,
    "High": 464.2,
    "Low": 440.7,
    "Vol.": "107.06K",
    "Change %": "4.67%"
  },
  {
    "Date": "Dec 14, 2015",
    "Price": 442,
    "Open": 434.7,
    "High": 449.5,
    "Low": 428.8,
    "Vol.": "218.92K",
    "Change %": "1.68%"
  },
  {
    "Date": "Dec 13, 2015",
    "Price": 434.7,
    "Open": 432.3,
    "High": 441,
    "Low": 420.8,
    "Vol.": "64.14K",
    "Change %": "0.56%"
  },
  {
    "Date": "Dec 12, 2015",
    "Price": 432.3,
    "Open": 449.8,
    "High": 467.7,
    "Low": 403.7,
    "Vol.": "211.44K",
    "Change %": "-3.90%"
  },
  {
    "Date": "Dec 11, 2015",
    "Price": 449.8,
    "Open": 415.5,
    "High": 453.4,
    "Low": 413.7,
    "Vol.": "175.06K",
    "Change %": "8.26%"
  },
  {
    "Date": "Dec 10, 2015",
    "Price": 415.5,
    "Open": 416,
    "High": 420.4,
    "Low": 409.5,
    "Vol.": "71.66K",
    "Change %": "-0.12%"
  },
  {
    "Date": "Dec 09, 2015",
    "Price": 416,
    "Open": 410.7,
    "High": 424.6,
    "Low": 403.3,
    "Vol.": "147.36K",
    "Change %": "1.30%"
  },
  {
    "Date": "Dec 08, 2015",
    "Price": 410.7,
    "Open": 394.3,
    "High": 411.1,
    "Low": 388,
    "Vol.": "74.36K",
    "Change %": "4.16%"
  },
  {
    "Date": "Dec 07, 2015",
    "Price": 394.3,
    "Open": 393.4,
    "High": 398.7,
    "Low": 381.7,
    "Vol.": "96.75K",
    "Change %": "0.23%"
  },
  {
    "Date": "Dec 06, 2015",
    "Price": 393.4,
    "Open": 386.7,
    "High": 402.2,
    "Low": 382.6,
    "Vol.": "131.86K",
    "Change %": "1.73%"
  },
  {
    "Date": "Dec 05, 2015",
    "Price": 386.7,
    "Open": 361.7,
    "High": 390.3,
    "Low": 361.5,
    "Vol.": "115.20K",
    "Change %": "6.92%"
  },
  {
    "Date": "Dec 04, 2015",
    "Price": 361.7,
    "Open": 360.3,
    "High": 364,
    "Low": 354.3,
    "Vol.": "60.55K",
    "Change %": "0.38%"
  },
  {
    "Date": "Dec 03, 2015",
    "Price": 360.3,
    "Open": 360,
    "High": 371.4,
    "Low": 355.5,
    "Vol.": "87.23K",
    "Change %": "0.09%"
  },
  {
    "Date": "Dec 02, 2015",
    "Price": 360,
    "Open": 361.8,
    "High": 363.4,
    "Low": 347.2,
    "Vol.": "92.45K",
    "Change %": "-0.50%"
  },
  {
    "Date": "Dec 01, 2015",
    "Price": 361.8,
    "Open": 378,
    "High": 379,
    "Low": 353.7,
    "Vol.": "111.91K",
    "Change %": "-4.28%"
  },
  {
    "Date": "Nov 30, 2015",
    "Price": 378,
    "Open": 370.8,
    "High": 382.6,
    "Low": 367.9,
    "Vol.": "129.77K",
    "Change %": "1.92%"
  },
  {
    "Date": "Nov 29, 2015",
    "Price": 370.8,
    "Open": 355.8,
    "High": 372.8,
    "Low": 354.5,
    "Vol.": "67.37K",
    "Change %": "4.22%"
  },
  {
    "Date": "Nov 28, 2015",
    "Price": 355.8,
    "Open": 359.5,
    "High": 360.1,
    "Low": 350.5,
    "Vol.": "56.17K",
    "Change %": "-1.03%"
  },
  {
    "Date": "Nov 27, 2015",
    "Price": 359.5,
    "Open": 353.7,
    "High": 363.9,
    "Low": 345.1,
    "Vol.": "103.48K",
    "Change %": "1.63%"
  },
  {
    "Date": "Nov 26, 2015",
    "Price": 353.7,
    "Open": 327.5,
    "High": 368.9,
    "Low": 327.4,
    "Vol.": "211.38K",
    "Change %": "8.01%"
  },
  {
    "Date": "Nov 25, 2015",
    "Price": 327.5,
    "Open": 318.4,
    "High": 330,
    "Low": 315.7,
    "Vol.": "77.68K",
    "Change %": "2.88%"
  },
  {
    "Date": "Nov 24, 2015",
    "Price": 318.4,
    "Open": 322.1,
    "High": 323.3,
    "Low": 315.5,
    "Vol.": "50.66K",
    "Change %": "-1.17%"
  },
  {
    "Date": "Nov 23, 2015",
    "Price": 322.1,
    "Open": 322.8,
    "High": 325,
    "Low": 319.9,
    "Vol.": "42.73K",
    "Change %": "-0.20%"
  },
  {
    "Date": "Nov 22, 2015",
    "Price": 322.8,
    "Open": 324.7,
    "High": 326.9,
    "Low": 319.4,
    "Vol.": "36.75K",
    "Change %": "-0.59%"
  },
  {
    "Date": "Nov 21, 2015",
    "Price": 324.7,
    "Open": 321.1,
    "High": 328.4,
    "Low": 318.4,
    "Vol.": "45.00K",
    "Change %": "1.11%"
  },
  {
    "Date": "Nov 20, 2015",
    "Price": 321.1,
    "Open": 325,
    "High": 327.1,
    "Low": 309.5,
    "Vol.": "109.99K",
    "Change %": "-1.19%"
  },
  {
    "Date": "Nov 19, 2015",
    "Price": 325,
    "Open": 335.9,
    "High": 335.6,
    "Low": 323.4,
    "Vol.": "86.38K",
    "Change %": "-3.26%"
  },
  {
    "Date": "Nov 18, 2015",
    "Price": 335.9,
    "Open": 333.9,
    "High": 337.4,
    "Low": 329.4,
    "Vol.": "78.36K",
    "Change %": "0.60%"
  },
  {
    "Date": "Nov 17, 2015",
    "Price": 333.9,
    "Open": 330.2,
    "High": 342.9,
    "Low": 328.1,
    "Vol.": "98.25K",
    "Change %": "1.12%"
  },
  {
    "Date": "Nov 16, 2015",
    "Price": 330.2,
    "Open": 317.5,
    "High": 332,
    "Low": 314.1,
    "Vol.": "87.14K",
    "Change %": "4.02%"
  },
  {
    "Date": "Nov 15, 2015",
    "Price": 317.5,
    "Open": 331.8,
    "High": 334.8,
    "Low": 314.2,
    "Vol.": "88.32K",
    "Change %": "-4.32%"
  },
  {
    "Date": "Nov 14, 2015",
    "Price": 331.8,
    "Open": 333.8,
    "High": 369.8,
    "Low": 326.4,
    "Vol.": "71.11K",
    "Change %": "-0.60%"
  },
  {
    "Date": "Nov 13, 2015",
    "Price": 333.8,
    "Open": 333.9,
    "High": 341.8,
    "Low": 323.9,
    "Vol.": "97.25K",
    "Change %": "-0.02%"
  },
  {
    "Date": "Nov 12, 2015",
    "Price": 333.9,
    "Open": 304.7,
    "High": 346.1,
    "Low": 306.1,
    "Vol.": "164.61K",
    "Change %": "9.56%"
  },
  {
    "Date": "Nov 11, 2015",
    "Price": 304.7,
    "Open": 336.7,
    "High": 341.8,
    "Low": 292.4,
    "Vol.": "263.96K",
    "Change %": "-9.50%"
  },
  {
    "Date": "Nov 10, 2015",
    "Price": 336.7,
    "Open": 380.2,
    "High": 381.4,
    "Low": 323.2,
    "Vol.": "210.29K",
    "Change %": "-11.45%"
  },
  {
    "Date": "Nov 09, 2015",
    "Price": 380.2,
    "Open": 371.6,
    "High": 385.1,
    "Low": 360.2,
    "Vol.": "125.54K",
    "Change %": "2.33%"
  },
  {
    "Date": "Nov 08, 2015",
    "Price": 371.6,
    "Open": 385.1,
    "High": 389.8,
    "Low": 365.5,
    "Vol.": "94.36K",
    "Change %": "-3.51%"
  },
  {
    "Date": "Nov 07, 2015",
    "Price": 385.1,
    "Open": 369.8,
    "High": 391.8,
    "Low": 369,
    "Vol.": "103.03K",
    "Change %": "4.13%"
  },
  {
    "Date": "Nov 06, 2015",
    "Price": 369.8,
    "Open": 382.7,
    "High": 396.4,
    "Low": 348.8,
    "Vol.": "255.28K",
    "Change %": "-3.37%"
  },
  {
    "Date": "Nov 05, 2015",
    "Price": 382.7,
    "Open": 400.9,
    "High": 447.2,
    "Low": 366.1,
    "Vol.": "302.95K",
    "Change %": "-4.54%"
  },
  {
    "Date": "Nov 04, 2015",
    "Price": 400.9,
    "Open": 396.5,
    "High": 492.8,
    "Low": 368.6,
    "Vol.": "517.73K",
    "Change %": "1.11%"
  },
  {
    "Date": "Nov 03, 2015",
    "Price": 396.5,
    "Open": 359.3,
    "High": 416.8,
    "Low": 354.6,
    "Vol.": "421.99K",
    "Change %": "10.36%"
  },
  {
    "Date": "Nov 02, 2015",
    "Price": 359.3,
    "Open": 323,
    "High": 365.8,
    "Low": 319.8,
    "Vol.": "223.10K",
    "Change %": "11.25%"
  },
  {
    "Date": "Nov 01, 2015",
    "Price": 323,
    "Open": 311.2,
    "High": 324.3,
    "Low": 304.7,
    "Vol.": "73.71K",
    "Change %": "3.76%"
  },
  {
    "Date": "Oct 31, 2015",
    "Price": 311.2,
    "Open": 327.1,
    "High": 333.3,
    "Low": 304.6,
    "Vol.": "105.83K",
    "Change %": "-4.85%"
  },
  {
    "Date": "Oct 30, 2015",
    "Price": 327.1,
    "Open": 313.6,
    "High": 334.9,
    "Low": 310.8,
    "Vol.": "156.49K",
    "Change %": "4.30%"
  },
  {
    "Date": "Oct 29, 2015",
    "Price": 313.6,
    "Open": 303.5,
    "High": 318.5,
    "Low": 300.2,
    "Vol.": "138.92K",
    "Change %": "3.32%"
  },
  {
    "Date": "Oct 28, 2015",
    "Price": 303.5,
    "Open": 294.7,
    "High": 307.5,
    "Low": 294,
    "Vol.": "116.41K",
    "Change %": "3.01%"
  },
  {
    "Date": "Oct 27, 2015",
    "Price": 294.7,
    "Open": 285.1,
    "High": 298.4,
    "Low": 285.1,
    "Vol.": "105.87K",
    "Change %": "3.34%"
  },
  {
    "Date": "Oct 26, 2015",
    "Price": 285.1,
    "Open": 287.9,
    "High": 287.6,
    "Low": 279.6,
    "Vol.": "73.21K",
    "Change %": "-0.94%"
  },
  {
    "Date": "Oct 25, 2015",
    "Price": 287.9,
    "Open": 282.6,
    "High": 295.6,
    "Low": 281.8,
    "Vol.": "113.90K",
    "Change %": "1.88%"
  },
  {
    "Date": "Oct 24, 2015",
    "Price": 282.6,
    "Open": 276.9,
    "High": 283,
    "Low": 277,
    "Vol.": "60.13K",
    "Change %": "2.04%"
  },
  {
    "Date": "Oct 23, 2015",
    "Price": 276.9,
    "Open": 274.4,
    "High": 279.8,
    "Low": 273.2,
    "Vol.": "69.32K",
    "Change %": "0.91%"
  },
  {
    "Date": "Oct 22, 2015",
    "Price": 274.4,
    "Open": 267.1,
    "High": 278.7,
    "Low": 266.8,
    "Vol.": "93.15K",
    "Change %": "2.74%"
  },
  {
    "Date": "Oct 21, 2015",
    "Price": 267.1,
    "Open": 269.8,
    "High": 272.2,
    "Low": 263.5,
    "Vol.": "59.64K",
    "Change %": "-0.98%"
  },
  {
    "Date": "Oct 20, 2015",
    "Price": 269.8,
    "Open": 263.8,
    "High": 272.1,
    "Low": 262.7,
    "Vol.": "75.40K",
    "Change %": "2.25%"
  },
  {
    "Date": "Oct 19, 2015",
    "Price": 263.8,
    "Open": 261.7,
    "High": 266,
    "Low": 259.9,
    "Vol.": "58.17K",
    "Change %": "0.82%"
  },
  {
    "Date": "Oct 18, 2015",
    "Price": 261.7,
    "Open": 269.6,
    "High": 272.4,
    "Low": 259.5,
    "Vol.": "52.27K",
    "Change %": "-2.93%"
  },
  {
    "Date": "Oct 17, 2015",
    "Price": 269.6,
    "Open": 262.9,
    "High": 275.4,
    "Low": 261.7,
    "Vol.": "113.84K",
    "Change %": "2.55%"
  },
  {
    "Date": "Oct 16, 2015",
    "Price": 262.9,
    "Open": 254.4,
    "High": 267.3,
    "Low": 253.9,
    "Vol.": "95.18K",
    "Change %": "3.31%"
  },
  {
    "Date": "Oct 15, 2015",
    "Price": 254.4,
    "Open": 252.3,
    "High": 256.8,
    "Low": 251.2,
    "Vol.": "60.64K",
    "Change %": "0.84%"
  },
  {
    "Date": "Oct 14, 2015",
    "Price": 252.3,
    "Open": 248.8,
    "High": 255.1,
    "Low": 248.3,
    "Vol.": "69.58K",
    "Change %": "1.43%"
  },
  {
    "Date": "Oct 13, 2015",
    "Price": 248.8,
    "Open": 245.4,
    "High": 251.2,
    "Low": 243.1,
    "Vol.": "74.88K",
    "Change %": "1.40%"
  },
  {
    "Date": "Oct 12, 2015",
    "Price": 245.4,
    "Open": 247.6,
    "High": 248,
    "Low": 244.6,
    "Vol.": "40.39K",
    "Change %": "-0.93%"
  },
  {
    "Date": "Oct 11, 2015",
    "Price": 247.6,
    "Open": 245.4,
    "High": 248.3,
    "Low": 244.5,
    "Vol.": "41.43K",
    "Change %": "0.94%"
  },
  {
    "Date": "Oct 10, 2015",
    "Price": 245.4,
    "Open": 244,
    "High": 245.9,
    "Low": 242.9,
    "Vol.": "38.96K",
    "Change %": "0.54%"
  },
  {
    "Date": "Oct 09, 2015",
    "Price": 244,
    "Open": 242.6,
    "High": 244.6,
    "Low": 241.3,
    "Vol.": "40.57K",
    "Change %": "0.60%"
  },
  {
    "Date": "Oct 08, 2015",
    "Price": 242.6,
    "Open": 243,
    "High": 244.8,
    "Low": 241.6,
    "Vol.": "44.15K",
    "Change %": "-0.16%"
  },
  {
    "Date": "Oct 07, 2015",
    "Price": 243,
    "Open": 246.1,
    "High": 247.3,
    "Low": 241.6,
    "Vol.": "62.60K",
    "Change %": "-1.28%"
  },
  {
    "Date": "Oct 06, 2015",
    "Price": 246.1,
    "Open": 240.1,
    "High": 247.6,
    "Low": 239.4,
    "Vol.": "78.84K",
    "Change %": "2.49%"
  },
  {
    "Date": "Oct 05, 2015",
    "Price": 240.1,
    "Open": 238.3,
    "High": 240.5,
    "Low": 236.4,
    "Vol.": "61.24K",
    "Change %": "0.76%"
  },
  {
    "Date": "Oct 04, 2015",
    "Price": 238.3,
    "Open": 238.6,
    "High": 277.6,
    "Low": 237.5,
    "Vol.": "31.85K",
    "Change %": "-0.10%"
  },
  {
    "Date": "Oct 03, 2015",
    "Price": 238.6,
    "Open": 236.7,
    "High": 239.5,
    "Low": 236.1,
    "Vol.": "43.31K",
    "Change %": "0.79%"
  },
  {
    "Date": "Oct 02, 2015",
    "Price": 236.7,
    "Open": 237.1,
    "High": 238.4,
    "Low": 235.1,
    "Vol.": "47.94K",
    "Change %": "-0.14%"
  },
  {
    "Date": "Oct 01, 2015",
    "Price": 237.1,
    "Open": 235.9,
    "High": 238.7,
    "Low": 234.7,
    "Vol.": "52.88K",
    "Change %": "0.47%"
  },
  {
    "Date": "Sep 30, 2015",
    "Price": 235.9,
    "Open": 236.7,
    "High": 237.8,
    "Low": 234.4,
    "Vol.": "50.52K",
    "Change %": "-0.33%"
  },
  {
    "Date": "Sep 29, 2015",
    "Price": 236.7,
    "Open": 238.9,
    "High": 240.4,
    "Low": 234.8,
    "Vol.": "57.30K",
    "Change %": "-0.90%"
  },
  {
    "Date": "Sep 28, 2015",
    "Price": 238.9,
    "Open": 232.5,
    "High": 240.4,
    "Low": 232.4,
    "Vol.": "64.28K",
    "Change %": "2.74%"
  },
  {
    "Date": "Sep 27, 2015",
    "Price": 232.5,
    "Open": 234.3,
    "High": 234.8,
    "Low": 231.8,
    "Vol.": "36.14K",
    "Change %": "-0.77%"
  },
  {
    "Date": "Sep 26, 2015",
    "Price": 234.3,
    "Open": 235,
    "High": 235.7,
    "Low": 232.7,
    "Vol.": "40.29K",
    "Change %": "-0.31%"
  },
  {
    "Date": "Sep 25, 2015",
    "Price": 235,
    "Open": 233.8,
    "High": 237.6,
    "Low": 232.7,
    "Vol.": "61.58K",
    "Change %": "0.54%"
  },
  {
    "Date": "Sep 24, 2015",
    "Price": 233.8,
    "Open": 229.9,
    "High": 235.8,
    "Low": 229.6,
    "Vol.": "72.12K",
    "Change %": "1.68%"
  },
  {
    "Date": "Sep 23, 2015",
    "Price": 229.9,
    "Open": 230,
    "High": 232.2,
    "Low": 228.5,
    "Vol.": "43.60K",
    "Change %": "-0.05%"
  },
  {
    "Date": "Sep 22, 2015",
    "Price": 230,
    "Open": 226.3,
    "High": 233.2,
    "Low": 224.1,
    "Vol.": "71.55K",
    "Change %": "1.63%"
  },
  {
    "Date": "Sep 21, 2015",
    "Price": 226.3,
    "Open": 231.1,
    "High": 231.6,
    "Low": 225,
    "Vol.": "53.43K",
    "Change %": "-2.06%"
  },
  {
    "Date": "Sep 20, 2015",
    "Price": 231.1,
    "Open": 231.1,
    "High": 232.7,
    "Low": 229.9,
    "Vol.": "33.15K",
    "Change %": "0.00%"
  },
  {
    "Date": "Sep 19, 2015",
    "Price": 231.1,
    "Open": 232.2,
    "High": 233.4,
    "Low": 230.2,
    "Vol.": "34.47K",
    "Change %": "-0.47%"
  },
  {
    "Date": "Sep 18, 2015",
    "Price": 232.2,
    "Open": 232.7,
    "High": 234.7,
    "Low": 230.6,
    "Vol.": "53.17K",
    "Change %": "-0.22%"
  },
  {
    "Date": "Sep 17, 2015",
    "Price": 232.7,
    "Open": 228.6,
    "High": 235.2,
    "Low": 227.9,
    "Vol.": "56.06K",
    "Change %": "1.80%"
  },
  {
    "Date": "Sep 16, 2015",
    "Price": 228.6,
    "Open": 229.5,
    "High": 230.9,
    "Low": 225.1,
    "Vol.": "51.91K",
    "Change %": "-0.41%"
  },
  {
    "Date": "Sep 15, 2015",
    "Price": 229.5,
    "Open": 229.9,
    "High": 242.8,
    "Low": 228,
    "Vol.": "49.52K",
    "Change %": "-0.17%"
  },
  {
    "Date": "Sep 14, 2015",
    "Price": 229.9,
    "Open": 230.2,
    "High": 232.6,
    "Low": 226,
    "Vol.": "61.10K",
    "Change %": "-0.12%"
  },
  {
    "Date": "Sep 13, 2015",
    "Price": 230.2,
    "Open": 235.6,
    "High": 236.2,
    "Low": 228.3,
    "Vol.": "51.60K",
    "Change %": "-2.30%"
  },
  {
    "Date": "Sep 12, 2015",
    "Price": 235.6,
    "Open": 239.9,
    "High": 240.3,
    "Low": 233.3,
    "Vol.": "43.77K",
    "Change %": "-1.79%"
  },
  {
    "Date": "Sep 11, 2015",
    "Price": 239.9,
    "Open": 238.1,
    "High": 241,
    "Low": 237.4,
    "Vol.": "45.77K",
    "Change %": "0.76%"
  },
  {
    "Date": "Sep 10, 2015",
    "Price": 238.1,
    "Open": 237.4,
    "High": 240.6,
    "Low": 234.3,
    "Vol.": "60.54K",
    "Change %": "0.28%"
  },
  {
    "Date": "Sep 09, 2015",
    "Price": 237.4,
    "Open": 243.2,
    "High": 244.3,
    "Low": 236.5,
    "Vol.": "69.26K",
    "Change %": "-2.40%"
  },
  {
    "Date": "Sep 08, 2015",
    "Price": 243.2,
    "Open": 239.6,
    "High": 246.4,
    "Low": 239.2,
    "Vol.": "76.35K",
    "Change %": "1.53%"
  },
  {
    "Date": "Sep 07, 2015",
    "Price": 239.6,
    "Open": 239.9,
    "High": 242.7,
    "Low": 237.5,
    "Vol.": "57.19K",
    "Change %": "-0.12%"
  },
  {
    "Date": "Sep 06, 2015",
    "Price": 239.9,
    "Open": 233.7,
    "High": 243.6,
    "Low": 234.7,
    "Vol.": "66.27K",
    "Change %": "2.65%"
  },
  {
    "Date": "Sep 05, 2015",
    "Price": 233.7,
    "Open": 230.3,
    "High": 235.6,
    "Low": 228.3,
    "Vol.": "48.28K",
    "Change %": "1.49%"
  },
  {
    "Date": "Sep 04, 2015",
    "Price": 230.3,
    "Open": 226.2,
    "High": 231.1,
    "Low": 225.8,
    "Vol.": "61.76K",
    "Change %": "1.79%"
  },
  {
    "Date": "Sep 03, 2015",
    "Price": 226.2,
    "Open": 228.6,
    "High": 229.6,
    "Low": 225.4,
    "Vol.": "54.15K",
    "Change %": "-1.06%"
  },
  {
    "Date": "Sep 02, 2015",
    "Price": 228.6,
    "Open": 227.2,
    "High": 230.6,
    "Low": 225.6,
    "Vol.": "58.77K",
    "Change %": "0.64%"
  },
  {
    "Date": "Sep 01, 2015",
    "Price": 227.2,
    "Open": 229.5,
    "High": 231.4,
    "Low": 225.8,
    "Vol.": "66.54K",
    "Change %": "-1.00%"
  },
  {
    "Date": "Aug 31, 2015",
    "Price": 229.5,
    "Open": 228.4,
    "High": 231.8,
    "Low": 224.2,
    "Vol.": "54.51K",
    "Change %": "0.47%"
  },
  {
    "Date": "Aug 30, 2015",
    "Price": 228.4,
    "Open": 228.5,
    "High": 232.3,
    "Low": 225.4,
    "Vol.": "39.81K",
    "Change %": "-0.04%"
  },
  {
    "Date": "Aug 29, 2015",
    "Price": 228.5,
    "Open": 231.6,
    "High": 233.1,
    "Low": 226.4,
    "Vol.": "43.74K",
    "Change %": "-1.36%"
  },
  {
    "Date": "Aug 28, 2015",
    "Price": 231.6,
    "Open": 222.7,
    "High": 234.8,
    "Low": 219.6,
    "Vol.": "90.66K",
    "Change %": "4.00%"
  },
  {
    "Date": "Aug 27, 2015",
    "Price": 222.7,
    "Open": 225,
    "High": 228.4,
    "Low": 222,
    "Vol.": "60.25K",
    "Change %": "-1.00%"
  },
  {
    "Date": "Aug 26, 2015",
    "Price": 225,
    "Open": 220.5,
    "High": 230.7,
    "Low": 218.8,
    "Vol.": "92.81K",
    "Change %": "2.02%"
  },
  {
    "Date": "Aug 25, 2015",
    "Price": 220.5,
    "Open": 211.4,
    "High": 226.6,
    "Low": 196.3,
    "Vol.": "190.79K",
    "Change %": "4.29%"
  },
  {
    "Date": "Aug 24, 2015",
    "Price": 211.4,
    "Open": 226.8,
    "High": 228.4,
    "Low": 207.8,
    "Vol.": "196.70K",
    "Change %": "-6.76%"
  },
  {
    "Date": "Aug 23, 2015",
    "Price": 226.8,
    "Open": 229.5,
    "High": 232.7,
    "Low": 224.3,
    "Vol.": "48.84K",
    "Change %": "-1.22%"
  },
  {
    "Date": "Aug 22, 2015",
    "Price": 229.5,
    "Open": 232.4,
    "High": 235.1,
    "Low": 221,
    "Vol.": "74.21K",
    "Change %": "-1.23%"
  },
  {
    "Date": "Aug 21, 2015",
    "Price": 232.4,
    "Open": 234.7,
    "High": 236.3,
    "Low": 230.5,
    "Vol.": "57.65K",
    "Change %": "-0.96%"
  },
  {
    "Date": "Aug 20, 2015",
    "Price": 234.7,
    "Open": 226,
    "High": 238,
    "Low": 225.5,
    "Vol.": "90.98K",
    "Change %": "3.83%"
  },
  {
    "Date": "Aug 19, 2015",
    "Price": 226,
    "Open": 246.7,
    "High": 247.9,
    "Low": 214.3,
    "Vol.": "245.82K",
    "Change %": "-8.40%"
  },
  {
    "Date": "Aug 18, 2015",
    "Price": 246.7,
    "Open": 257.1,
    "High": 257.5,
    "Low": 245.7,
    "Vol.": "94.50K",
    "Change %": "-4.05%"
  },
  {
    "Date": "Aug 17, 2015",
    "Price": 257.1,
    "Open": 257.1,
    "High": 259.9,
    "Low": 252.9,
    "Vol.": "47.88K",
    "Change %": "0.00%"
  },
  {
    "Date": "Aug 16, 2015",
    "Price": 257.1,
    "Open": 260.5,
    "High": 261.9,
    "Low": 254.6,
    "Vol.": "69.04K",
    "Change %": "-1.31%"
  },
  {
    "Date": "Aug 15, 2015",
    "Price": 260.5,
    "Open": 265,
    "High": 266.5,
    "Low": 259.4,
    "Vol.": "38.91K",
    "Change %": "-1.70%"
  },
  {
    "Date": "Aug 14, 2015",
    "Price": 265,
    "Open": 263.4,
    "High": 267.2,
    "Low": 260.2,
    "Vol.": "52.33K",
    "Change %": "0.60%"
  },
  {
    "Date": "Aug 13, 2015",
    "Price": 263.4,
    "Open": 267.7,
    "High": 268.4,
    "Low": 261.3,
    "Vol.": "56.49K",
    "Change %": "-1.58%"
  },
  {
    "Date": "Aug 12, 2015",
    "Price": 267.7,
    "Open": 269,
    "High": 271.5,
    "Low": 263.7,
    "Vol.": "56.73K",
    "Change %": "-0.51%"
  },
  {
    "Date": "Aug 11, 2015",
    "Price": 269,
    "Open": 263.3,
    "High": 269.9,
    "Low": 261.4,
    "Vol.": "51.36K",
    "Change %": "2.18%"
  },
  {
    "Date": "Aug 10, 2015",
    "Price": 263.3,
    "Open": 263.9,
    "High": 266.6,
    "Low": 260.5,
    "Vol.": "48.57K",
    "Change %": "-0.22%"
  },
  {
    "Date": "Aug 09, 2015",
    "Price": 263.9,
    "Open": 258.6,
    "High": 266.8,
    "Low": 258.6,
    "Vol.": "57.48K",
    "Change %": "2.04%"
  },
  {
    "Date": "Aug 08, 2015",
    "Price": 258.6,
    "Open": 277.9,
    "High": 278.9,
    "Low": 257.4,
    "Vol.": "82.54K",
    "Change %": "-6.94%"
  },
  {
    "Date": "Aug 07, 2015",
    "Price": 277.9,
    "Open": 278,
    "High": 279.6,
    "Low": 274.3,
    "Vol.": "42.81K",
    "Change %": "-0.04%"
  },
  {
    "Date": "Aug 06, 2015",
    "Price": 278,
    "Open": 281.7,
    "High": 282,
    "Low": 276.5,
    "Vol.": "33.26K",
    "Change %": "-1.32%"
  },
  {
    "Date": "Aug 05, 2015",
    "Price": 281.7,
    "Open": 284.3,
    "High": 285.5,
    "Low": 280.5,
    "Vol.": "38.29K",
    "Change %": "-0.91%"
  },
  {
    "Date": "Aug 04, 2015",
    "Price": 284.3,
    "Open": 281.6,
    "High": 285.7,
    "Low": 279.6,
    "Vol.": "44.84K",
    "Change %": "0.97%"
  },
  {
    "Date": "Aug 03, 2015",
    "Price": 281.6,
    "Open": 281.4,
    "High": 285,
    "Low": 278.9,
    "Vol.": "45.89K",
    "Change %": "0.08%"
  },
  {
    "Date": "Aug 02, 2015",
    "Price": 281.4,
    "Open": 280.5,
    "High": 282.5,
    "Low": 275.9,
    "Vol.": "35.67K",
    "Change %": "0.32%"
  },
  {
    "Date": "Aug 01, 2015",
    "Price": 280.5,
    "Open": 283.7,
    "High": 284.5,
    "Low": 276.3,
    "Vol.": "39.43K",
    "Change %": "-1.15%"
  },
  {
    "Date": "Jul 31, 2015",
    "Price": 283.7,
    "Open": 287,
    "High": 288.7,
    "Low": 280.8,
    "Vol.": "49.21K",
    "Change %": "-1.15%"
  },
  {
    "Date": "Jul 30, 2015",
    "Price": 287,
    "Open": 288.4,
    "High": 289.9,
    "Low": 284.9,
    "Vol.": "44.79K",
    "Change %": "-0.47%"
  },
  {
    "Date": "Jul 29, 2015",
    "Price": 288.4,
    "Open": 293.7,
    "High": 294.7,
    "Low": 286.9,
    "Vol.": "50.67K",
    "Change %": "-1.81%"
  },
  {
    "Date": "Jul 28, 2015",
    "Price": 293.7,
    "Open": 293,
    "High": 296.7,
    "Low": 291.7,
    "Vol.": "49.07K",
    "Change %": "0.24%"
  },
  {
    "Date": "Jul 27, 2015",
    "Price": 293,
    "Open": 291.8,
    "High": 295.8,
    "Low": 285.4,
    "Vol.": "69.71K",
    "Change %": "0.42%"
  },
  {
    "Date": "Jul 26, 2015",
    "Price": 291.8,
    "Open": 288.7,
    "High": 293.3,
    "Low": 286.8,
    "Vol.": "30.99K",
    "Change %": "1.05%"
  },
  {
    "Date": "Jul 25, 2015",
    "Price": 288.7,
    "Open": 288.4,
    "High": 291.2,
    "Low": 284.7,
    "Vol.": "41.65K",
    "Change %": "0.13%"
  },
  {
    "Date": "Jul 24, 2015",
    "Price": 288.4,
    "Open": 275.5,
    "High": 289.8,
    "Low": 274.3,
    "Vol.": "74.36K",
    "Change %": "4.66%"
  },
  {
    "Date": "Jul 23, 2015",
    "Price": 275.5,
    "Open": 276.5,
    "High": 277.9,
    "Low": 274.5,
    "Vol.": "35.66K",
    "Change %": "-0.34%"
  },
  {
    "Date": "Jul 22, 2015",
    "Price": 276.5,
    "Open": 275.1,
    "High": 277.4,
    "Low": 273.1,
    "Vol.": "41.97K",
    "Change %": "0.50%"
  },
  {
    "Date": "Jul 21, 2015",
    "Price": 275.1,
    "Open": 277.7,
    "High": 281,
    "Low": 274.2,
    "Vol.": "49.05K",
    "Change %": "-0.93%"
  },
  {
    "Date": "Jul 20, 2015",
    "Price": 277.7,
    "Open": 273.2,
    "High": 278.9,
    "Low": 271.8,
    "Vol.": "46.60K",
    "Change %": "1.65%"
  },
  {
    "Date": "Jul 19, 2015",
    "Price": 273.2,
    "Open": 274,
    "High": 277.1,
    "Low": 271.9,
    "Vol.": "30.20K",
    "Change %": "-0.32%"
  },
  {
    "Date": "Jul 18, 2015",
    "Price": 274,
    "Open": 279.6,
    "High": 282.5,
    "Low": 243.2,
    "Vol.": "55.34K",
    "Change %": "-1.99%"
  },
  {
    "Date": "Jul 17, 2015",
    "Price": 279.6,
    "Open": 276.6,
    "High": 280.8,
    "Low": 271.2,
    "Vol.": "62.12K",
    "Change %": "1.10%"
  },
  {
    "Date": "Jul 16, 2015",
    "Price": 276.6,
    "Open": 283.4,
    "High": 290.8,
    "Low": 273.3,
    "Vol.": "121.32K",
    "Change %": "-2.41%"
  },
  {
    "Date": "Jul 15, 2015",
    "Price": 283.4,
    "Open": 287,
    "High": 292.9,
    "Low": 283.2,
    "Vol.": "59.58K",
    "Change %": "-1.23%"
  },
  {
    "Date": "Jul 14, 2015",
    "Price": 287,
    "Open": 290.4,
    "High": 297,
    "Low": 285.2,
    "Vol.": "60.62K",
    "Change %": "-1.17%"
  },
  {
    "Date": "Jul 13, 2015",
    "Price": 290.4,
    "Open": 310.4,
    "High": 310.9,
    "Low": 276.9,
    "Vol.": "146.85K",
    "Change %": "-6.47%"
  },
  {
    "Date": "Jul 12, 2015",
    "Price": 310.4,
    "Open": 292,
    "High": 315.9,
    "Low": 291.3,
    "Vol.": "120.70K",
    "Change %": "6.33%"
  },
  {
    "Date": "Jul 11, 2015",
    "Price": 292,
    "Open": 283.6,
    "High": 298.8,
    "Low": 282.3,
    "Vol.": "46.49K",
    "Change %": "2.94%"
  },
  {
    "Date": "Jul 10, 2015",
    "Price": 283.6,
    "Open": 269.1,
    "High": 297.9,
    "Low": 266.9,
    "Vol.": "117.17K",
    "Change %": "5.38%"
  },
  {
    "Date": "Jul 09, 2015",
    "Price": 269.1,
    "Open": 268.6,
    "High": 272.3,
    "Low": 265.1,
    "Vol.": "48.39K",
    "Change %": "0.19%"
  },
  {
    "Date": "Jul 08, 2015",
    "Price": 268.6,
    "Open": 266.2,
    "High": 273.6,
    "Low": 263.2,
    "Vol.": "45.29K",
    "Change %": "0.91%"
  },
  {
    "Date": "Jul 07, 2015",
    "Price": 266.2,
    "Open": 269.1,
    "High": 271.3,
    "Low": 263.2,
    "Vol.": "41.61K",
    "Change %": "-1.07%"
  },
  {
    "Date": "Jul 06, 2015",
    "Price": 269.1,
    "Open": 270.1,
    "High": 277.5,
    "Low": 266.5,
    "Vol.": "90.58K",
    "Change %": "-0.39%"
  },
  {
    "Date": "Jul 05, 2015",
    "Price": 270.1,
    "Open": 260.5,
    "High": 274.1,
    "Low": 257.6,
    "Vol.": "48.45K",
    "Change %": "3.68%"
  },
  {
    "Date": "Jul 04, 2015",
    "Price": 260.5,
    "Open": 255.4,
    "High": 261.1,
    "Low": 253.4,
    "Vol.": "32.95K",
    "Change %": "2.02%"
  },
  {
    "Date": "Jul 03, 2015",
    "Price": 255.4,
    "Open": 254.9,
    "High": 256.7,
    "Low": 252.4,
    "Vol.": "36.58K",
    "Change %": "0.20%"
  },
  {
    "Date": "Jul 02, 2015",
    "Price": 254.9,
    "Open": 257.6,
    "High": 261.3,
    "Low": 253.1,
    "Vol.": "45.01K",
    "Change %": "-1.06%"
  },
  {
    "Date": "Jul 01, 2015",
    "Price": 257.6,
    "Open": 264.1,
    "High": 265,
    "Low": 254.4,
    "Vol.": "66.94K",
    "Change %": "-2.46%"
  },
  {
    "Date": "Jun 30, 2015",
    "Price": 264.1,
    "Open": 257,
    "High": 268.7,
    "Low": 255.4,
    "Vol.": "116.53K",
    "Change %": "2.78%"
  },
  {
    "Date": "Jun 29, 2015",
    "Price": 257,
    "Open": 248.9,
    "High": 257.5,
    "Low": 248,
    "Vol.": "92.64K",
    "Change %": "3.25%"
  },
  {
    "Date": "Jun 28, 2015",
    "Price": 248.9,
    "Open": 250.7,
    "High": 251.6,
    "Low": 246.6,
    "Vol.": "39.89K",
    "Change %": "-0.74%"
  },
  {
    "Date": "Jun 27, 2015",
    "Price": 250.7,
    "Open": 242.9,
    "High": 251.6,
    "Low": 241.8,
    "Vol.": "54.70K",
    "Change %": "3.20%"
  },
  {
    "Date": "Jun 26, 2015",
    "Price": 242.9,
    "Open": 242.6,
    "High": 243.5,
    "Low": 240.1,
    "Vol.": "37.62K",
    "Change %": "0.16%"
  },
  {
    "Date": "Jun 25, 2015",
    "Price": 242.6,
    "Open": 240.6,
    "High": 243.6,
    "Low": 239.3,
    "Vol.": "40.36K",
    "Change %": "0.83%"
  },
  {
    "Date": "Jun 24, 2015",
    "Price": 240.6,
    "Open": 243.8,
    "High": 244.5,
    "Low": 239.1,
    "Vol.": "47.11K",
    "Change %": "-1.31%"
  },
  {
    "Date": "Jun 23, 2015",
    "Price": 243.8,
    "Open": 247.5,
    "High": 247.7,
    "Low": 242.3,
    "Vol.": "38.43K",
    "Change %": "-1.50%"
  },
  {
    "Date": "Jun 22, 2015",
    "Price": 247.5,
    "Open": 244.1,
    "High": 248.6,
    "Low": 243.2,
    "Vol.": "47.59K",
    "Change %": "1.38%"
  },
  {
    "Date": "Jun 21, 2015",
    "Price": 244.1,
    "Open": 245,
    "High": 246,
    "Low": 240.9,
    "Vol.": "25.15K",
    "Change %": "-0.36%"
  },
  {
    "Date": "Jun 20, 2015",
    "Price": 245,
    "Open": 244.1,
    "High": 246.6,
    "Low": 238.7,
    "Vol.": "51.28K",
    "Change %": "0.35%"
  },
  {
    "Date": "Jun 19, 2015",
    "Price": 244.1,
    "Open": 248.4,
    "High": 250.8,
    "Low": 243.6,
    "Vol.": "84.70K",
    "Change %": "-1.73%"
  },
  {
    "Date": "Jun 18, 2015",
    "Price": 248.4,
    "Open": 247.4,
    "High": 251.9,
    "Low": 242.5,
    "Vol.": "78.14K",
    "Change %": "0.43%"
  },
  {
    "Date": "Jun 17, 2015",
    "Price": 247.4,
    "Open": 249.8,
    "High": 258.5,
    "Low": 245.1,
    "Vol.": "121.62K",
    "Change %": "-0.98%"
  },
  {
    "Date": "Jun 16, 2015",
    "Price": 249.8,
    "Open": 237,
    "High": 254.1,
    "Low": 235.7,
    "Vol.": "122.47K",
    "Change %": "5.41%"
  },
  {
    "Date": "Jun 15, 2015",
    "Price": 237,
    "Open": 233.8,
    "High": 238.6,
    "Low": 233.3,
    "Vol.": "63.47K",
    "Change %": "1.39%"
  },
  {
    "Date": "Jun 14, 2015",
    "Price": 233.8,
    "Open": 232.5,
    "High": 235.5,
    "Low": 232.1,
    "Vol.": "32.90K",
    "Change %": "0.55%"
  },
  {
    "Date": "Jun 13, 2015",
    "Price": 232.5,
    "Open": 230.5,
    "High": 233.1,
    "Low": 229,
    "Vol.": "38.01K",
    "Change %": "0.88%"
  },
  {
    "Date": "Jun 12, 2015",
    "Price": 230.5,
    "Open": 229.9,
    "High": 231.6,
    "Low": 229.3,
    "Vol.": "40.75K",
    "Change %": "0.25%"
  },
  {
    "Date": "Jun 11, 2015",
    "Price": 229.9,
    "Open": 228.8,
    "High": 230.6,
    "Low": 228.5,
    "Vol.": "38.00K",
    "Change %": "0.48%"
  },
  {
    "Date": "Jun 10, 2015",
    "Price": 228.8,
    "Open": 229.6,
    "High": 230.4,
    "Low": 227.8,
    "Vol.": "41.64K",
    "Change %": "-0.34%"
  },
  {
    "Date": "Jun 09, 2015",
    "Price": 229.6,
    "Open": 228.6,
    "High": 231.4,
    "Low": 227.5,
    "Vol.": "54.84K",
    "Change %": "0.43%"
  },
  {
    "Date": "Jun 08, 2015",
    "Price": 228.6,
    "Open": 223.5,
    "High": 229.9,
    "Low": 223,
    "Vol.": "74.15K",
    "Change %": "2.28%"
  },
  {
    "Date": "Jun 07, 2015",
    "Price": 223.5,
    "Open": 224.7,
    "High": 226.4,
    "Low": 222.2,
    "Vol.": "40.48K",
    "Change %": "-0.57%"
  },
  {
    "Date": "Jun 06, 2015",
    "Price": 224.7,
    "Open": 225.3,
    "High": 225.8,
    "Low": 223.5,
    "Vol.": "22.47K",
    "Change %": "-0.24%"
  },
  {
    "Date": "Jun 05, 2015",
    "Price": 225.3,
    "Open": 224.2,
    "High": 226.4,
    "Low": 222.1,
    "Vol.": "56.46K",
    "Change %": "0.48%"
  },
  {
    "Date": "Jun 04, 2015",
    "Price": 224.2,
    "Open": 225.6,
    "High": 226.7,
    "Low": 223.5,
    "Vol.": "44.06K",
    "Change %": "-0.61%"
  },
  {
    "Date": "Jun 03, 2015",
    "Price": 225.6,
    "Open": 225.7,
    "High": 227.9,
    "Low": 223.7,
    "Vol.": "54.35K",
    "Change %": "-0.07%"
  },
  {
    "Date": "Jun 02, 2015",
    "Price": 225.7,
    "Open": 223.1,
    "High": 227.4,
    "Low": 222.3,
    "Vol.": "60.81K",
    "Change %": "1.17%"
  },
  {
    "Date": "Jun 01, 2015",
    "Price": 223.1,
    "Open": 229.8,
    "High": 231.8,
    "Low": 221,
    "Vol.": "87.06K",
    "Change %": "-2.92%"
  },
  {
    "Date": "May 31, 2015",
    "Price": 229.8,
    "Open": 233.2,
    "High": 234,
    "Low": 229.1,
    "Vol.": "39.00K",
    "Change %": "-1.45%"
  },
  {
    "Date": "May 30, 2015",
    "Price": 233.2,
    "Open": 237,
    "High": 237.1,
    "Low": 231.6,
    "Vol.": "41.63K",
    "Change %": "-1.61%"
  },
  {
    "Date": "May 29, 2015",
    "Price": 237,
    "Open": 237.3,
    "High": 237.9,
    "Low": 235.1,
    "Vol.": "38.92K",
    "Change %": "-0.12%"
  },
  {
    "Date": "May 28, 2015",
    "Price": 237.3,
    "Open": 237.3,
    "High": 238.4,
    "Low": 236.2,
    "Vol.": "35.75K",
    "Change %": "0.00%"
  },
  {
    "Date": "May 27, 2015",
    "Price": 237.3,
    "Open": 237.8,
    "High": 238.9,
    "Low": 235.9,
    "Vol.": "48.03K",
    "Change %": "-0.23%"
  },
  {
    "Date": "May 26, 2015",
    "Price": 237.8,
    "Open": 237.4,
    "High": 239,
    "Low": 235.6,
    "Vol.": "37.08K",
    "Change %": "0.18%"
  },
  {
    "Date": "May 25, 2015",
    "Price": 237.4,
    "Open": 241,
    "High": 241.8,
    "Low": 235.8,
    "Vol.": "26.39K",
    "Change %": "-1.48%"
  },
  {
    "Date": "May 24, 2015",
    "Price": 241,
    "Open": 238.9,
    "High": 242.4,
    "Low": 237.5,
    "Vol.": "30.26K",
    "Change %": "0.85%"
  },
  {
    "Date": "May 23, 2015",
    "Price": 238.9,
    "Open": 240.4,
    "High": 241.7,
    "Low": 238.1,
    "Vol.": "36.03K",
    "Change %": "-0.59%"
  },
  {
    "Date": "May 22, 2015",
    "Price": 240.4,
    "Open": 235.4,
    "High": 242,
    "Low": 234.6,
    "Vol.": "74.11K",
    "Change %": "2.12%"
  },
  {
    "Date": "May 21, 2015",
    "Price": 235.4,
    "Open": 234,
    "High": 236.6,
    "Low": 233.6,
    "Vol.": "42.94K",
    "Change %": "0.61%"
  },
  {
    "Date": "May 20, 2015",
    "Price": 234,
    "Open": 232,
    "High": 235.2,
    "Low": 231.5,
    "Vol.": "49.69K",
    "Change %": "0.84%"
  },
  {
    "Date": "May 19, 2015",
    "Price": 232,
    "Open": 232.6,
    "High": 234.5,
    "Low": 231.3,
    "Vol.": "40.94K",
    "Change %": "-0.27%"
  },
  {
    "Date": "May 18, 2015",
    "Price": 232.6,
    "Open": 236.3,
    "High": 237.1,
    "Low": 231.5,
    "Vol.": "53.14K",
    "Change %": "-1.55%"
  },
  {
    "Date": "May 17, 2015",
    "Price": 236.3,
    "Open": 236.2,
    "High": 237.8,
    "Low": 235.4,
    "Vol.": "28.43K",
    "Change %": "0.03%"
  },
  {
    "Date": "May 16, 2015",
    "Price": 236.2,
    "Open": 237.2,
    "High": 237.8,
    "Low": 234.6,
    "Vol.": "27.05K",
    "Change %": "-0.41%"
  },
  {
    "Date": "May 15, 2015",
    "Price": 237.2,
    "Open": 236.9,
    "High": 238.8,
    "Low": 235.5,
    "Vol.": "46.03K",
    "Change %": "0.13%"
  },
  {
    "Date": "May 14, 2015",
    "Price": 236.9,
    "Open": 236.4,
    "High": 239.2,
    "Low": 232.4,
    "Vol.": "71.02K",
    "Change %": "0.22%"
  },
  {
    "Date": "May 13, 2015",
    "Price": 236.4,
    "Open": 241.6,
    "High": 243.9,
    "Low": 234.1,
    "Vol.": "84.43K",
    "Change %": "-2.15%"
  },
  {
    "Date": "May 12, 2015",
    "Price": 241.6,
    "Open": 241.8,
    "High": 243,
    "Low": 239.2,
    "Vol.": "40.08K",
    "Change %": "-0.10%"
  },
  {
    "Date": "May 11, 2015",
    "Price": 241.8,
    "Open": 240,
    "High": 243.9,
    "Low": 238.9,
    "Vol.": "57.17K",
    "Change %": "0.77%"
  },
  {
    "Date": "May 10, 2015",
    "Price": 240,
    "Open": 241.4,
    "High": 244.8,
    "Low": 238.2,
    "Vol.": "44.00K",
    "Change %": "-0.60%"
  },
  {
    "Date": "May 09, 2015",
    "Price": 241.4,
    "Open": 243.7,
    "High": 247.9,
    "Low": 238.5,
    "Vol.": "62.79K",
    "Change %": "-0.96%"
  },
  {
    "Date": "May 08, 2015",
    "Price": 243.7,
    "Open": 237.7,
    "High": 247,
    "Low": 235.8,
    "Vol.": "87.50K",
    "Change %": "2.53%"
  },
  {
    "Date": "May 07, 2015",
    "Price": 237.7,
    "Open": 230,
    "High": 240.3,
    "Low": 228.3,
    "Vol.": "91.05K",
    "Change %": "3.35%"
  },
  {
    "Date": "May 06, 2015",
    "Price": 230,
    "Open": 235.8,
    "High": 237.1,
    "Low": 228.2,
    "Vol.": "103.66K",
    "Change %": "-2.46%"
  },
  {
    "Date": "May 05, 2015",
    "Price": 235.8,
    "Open": 239,
    "High": 239.6,
    "Low": 231.8,
    "Vol.": "77.87K",
    "Change %": "-1.32%"
  },
  {
    "Date": "May 04, 2015",
    "Price": 239,
    "Open": 240,
    "High": 243.2,
    "Low": 237.4,
    "Vol.": "69.12K",
    "Change %": "-0.43%"
  },
  {
    "Date": "May 03, 2015",
    "Price": 240,
    "Open": 235.3,
    "High": 243.6,
    "Low": 233.8,
    "Vol.": "55.72K",
    "Change %": "1.98%"
  },
  {
    "Date": "May 02, 2015",
    "Price": 235.3,
    "Open": 233.2,
    "High": 236.4,
    "Low": 231.7,
    "Vol.": "37.08K",
    "Change %": "0.91%"
  },
  {
    "Date": "May 01, 2015",
    "Price": 233.2,
    "Open": 235.8,
    "High": 239.4,
    "Low": 232.4,
    "Vol.": "60.14K",
    "Change %": "-1.09%"
  },
  {
    "Date": "Apr 30, 2015",
    "Price": 235.8,
    "Open": 225.4,
    "High": 240,
    "Low": 224.7,
    "Vol.": "112.24K",
    "Change %": "4.59%"
  },
  {
    "Date": "Apr 29, 2015",
    "Price": 225.4,
    "Open": 225.8,
    "High": 227.2,
    "Low": 222.3,
    "Vol.": "60.89K",
    "Change %": "-0.17%"
  },
  {
    "Date": "Apr 28, 2015",
    "Price": 225.8,
    "Open": 229,
    "High": 229.9,
    "Low": 222,
    "Vol.": "65.97K",
    "Change %": "-1.38%"
  },
  {
    "Date": "Apr 27, 2015",
    "Price": 229,
    "Open": 218.7,
    "High": 242.6,
    "Low": 216.6,
    "Vol.": "123.41K",
    "Change %": "4.69%"
  },
  {
    "Date": "Apr 26, 2015",
    "Price": 218.7,
    "Open": 226.1,
    "High": 226.7,
    "Low": 214.1,
    "Vol.": "100.77K",
    "Change %": "-3.29%"
  },
  {
    "Date": "Apr 25, 2015",
    "Price": 226.1,
    "Open": 231.1,
    "High": 232.3,
    "Low": 223.1,
    "Vol.": "43.78K",
    "Change %": "-2.14%"
  },
  {
    "Date": "Apr 24, 2015",
    "Price": 231.1,
    "Open": 235.4,
    "High": 236.6,
    "Low": 229.1,
    "Vol.": "69.78K",
    "Change %": "-1.83%"
  },
  {
    "Date": "Apr 23, 2015",
    "Price": 235.4,
    "Open": 233.8,
    "High": 236.1,
    "Low": 232.6,
    "Vol.": "42.45K",
    "Change %": "0.69%"
  },
  {
    "Date": "Apr 22, 2015",
    "Price": 233.8,
    "Open": 233.7,
    "High": 238.4,
    "Low": 231.8,
    "Vol.": "77.56K",
    "Change %": "0.02%"
  },
  {
    "Date": "Apr 21, 2015",
    "Price": 233.7,
    "Open": 224.2,
    "High": 235.3,
    "Low": 223.3,
    "Vol.": "68.35K",
    "Change %": "4.23%"
  },
  {
    "Date": "Apr 20, 2015",
    "Price": 224.2,
    "Open": 223,
    "High": 226.7,
    "Low": 221.6,
    "Vol.": "44.87K",
    "Change %": "0.55%"
  },
  {
    "Date": "Apr 19, 2015",
    "Price": 223,
    "Open": 223.4,
    "High": 226.9,
    "Low": 222,
    "Vol.": "35.50K",
    "Change %": "-0.15%"
  },
  {
    "Date": "Apr 18, 2015",
    "Price": 223.4,
    "Open": 222.6,
    "High": 224.5,
    "Low": 220.6,
    "Vol.": "36.54K",
    "Change %": "0.34%"
  },
  {
    "Date": "Apr 17, 2015",
    "Price": 222.6,
    "Open": 228,
    "High": 229.3,
    "Low": 220.6,
    "Vol.": "66.92K",
    "Change %": "-2.36%"
  },
  {
    "Date": "Apr 16, 2015",
    "Price": 228,
    "Open": 223,
    "High": 229.5,
    "Low": 222.9,
    "Vol.": "84.89K",
    "Change %": "2.25%"
  },
  {
    "Date": "Apr 15, 2015",
    "Price": 223,
    "Open": 218,
    "High": 223.6,
    "Low": 217.1,
    "Vol.": "77.23K",
    "Change %": "2.28%"
  },
  {
    "Date": "Apr 14, 2015",
    "Price": 218,
    "Open": 223.6,
    "High": 224.7,
    "Low": 214.3,
    "Vol.": "115.19K",
    "Change %": "-2.50%"
  },
  {
    "Date": "Apr 13, 2015",
    "Price": 223.6,
    "Open": 235.9,
    "High": 236.8,
    "Low": 220.4,
    "Vol.": "105.15K",
    "Change %": "-5.20%"
  },
  {
    "Date": "Apr 12, 2015",
    "Price": 235.9,
    "Open": 236.5,
    "High": 237.5,
    "Low": 232.3,
    "Vol.": "33.03K",
    "Change %": "-0.27%"
  },
  {
    "Date": "Apr 11, 2015",
    "Price": 236.5,
    "Open": 234.7,
    "High": 240,
    "Low": 233.1,
    "Vol.": "51.99K",
    "Change %": "0.75%"
  },
  {
    "Date": "Apr 10, 2015",
    "Price": 234.7,
    "Open": 243.3,
    "High": 244.1,
    "Low": 231.3,
    "Vol.": "100.20K",
    "Change %": "-3.53%"
  },
  {
    "Date": "Apr 09, 2015",
    "Price": 243.3,
    "Open": 244.6,
    "High": 246.2,
    "Low": 237.6,
    "Vol.": "69.19K",
    "Change %": "-0.51%"
  },
  {
    "Date": "Apr 08, 2015",
    "Price": 244.6,
    "Open": 253,
    "High": 254.3,
    "Low": 242.6,
    "Vol.": "102.65K",
    "Change %": "-3.32%"
  },
  {
    "Date": "Apr 07, 2015",
    "Price": 253,
    "Open": 255,
    "High": 255.6,
    "Low": 250.1,
    "Vol.": "44.79K",
    "Change %": "-0.78%"
  },
  {
    "Date": "Apr 06, 2015",
    "Price": 255,
    "Open": 259.6,
    "High": 261.5,
    "Low": 252.3,
    "Vol.": "45.93K",
    "Change %": "-1.80%"
  },
  {
    "Date": "Apr 05, 2015",
    "Price": 259.6,
    "Open": 252.9,
    "High": 260.3,
    "Low": 250.6,
    "Vol.": "43.83K",
    "Change %": "2.67%"
  },
  {
    "Date": "Apr 04, 2015",
    "Price": 252.9,
    "Open": 254.5,
    "High": 255.2,
    "Low": 250.3,
    "Vol.": "30.72K",
    "Change %": "-0.62%"
  },
  {
    "Date": "Apr 03, 2015",
    "Price": 254.5,
    "Open": 252.6,
    "High": 256.5,
    "Low": 251.3,
    "Vol.": "71.74K",
    "Change %": "0.74%"
  },
  {
    "Date": "Apr 02, 2015",
    "Price": 252.6,
    "Open": 246.2,
    "High": 254.9,
    "Low": 244.3,
    "Vol.": "81.37K",
    "Change %": "2.58%"
  },
  {
    "Date": "Apr 01, 2015",
    "Price": 246.2,
    "Open": 244.1,
    "High": 247.7,
    "Low": 239.6,
    "Vol.": "67.08K",
    "Change %": "0.86%"
  },
  {
    "Date": "Mar 31, 2015",
    "Price": 244.1,
    "Open": 246.8,
    "High": 248.7,
    "Low": 241.2,
    "Vol.": "75.33K",
    "Change %": "-1.07%"
  },
  {
    "Date": "Mar 30, 2015",
    "Price": 246.8,
    "Open": 242.1,
    "High": 248.8,
    "Low": 236.6,
    "Vol.": "85.33K",
    "Change %": "1.95%"
  },
  {
    "Date": "Mar 29, 2015",
    "Price": 242.1,
    "Open": 252,
    "High": 252.8,
    "Low": 238.9,
    "Vol.": "77.54K",
    "Change %": "-3.94%"
  },
  {
    "Date": "Mar 28, 2015",
    "Price": 252,
    "Open": 247.2,
    "High": 254.3,
    "Low": 246.3,
    "Vol.": "55.06K",
    "Change %": "1.95%"
  },
  {
    "Date": "Mar 27, 2015",
    "Price": 247.2,
    "Open": 248,
    "High": 250.1,
    "Low": 244.5,
    "Vol.": "62.56K",
    "Change %": "-0.33%"
  },
  {
    "Date": "Mar 26, 2015",
    "Price": 248,
    "Open": 246.4,
    "High": 254.7,
    "Low": 243.5,
    "Vol.": "89.47K",
    "Change %": "0.67%"
  },
  {
    "Date": "Mar 25, 2015",
    "Price": 246.4,
    "Open": 246.7,
    "High": 249.2,
    "Low": 234.8,
    "Vol.": "131.44K",
    "Change %": "-0.14%"
  },
  {
    "Date": "Mar 24, 2015",
    "Price": 246.7,
    "Open": 265.5,
    "High": 267,
    "Low": 242.7,
    "Vol.": "151.09K",
    "Change %": "-7.06%"
  },
  {
    "Date": "Mar 23, 2015",
    "Price": 265.5,
    "Open": 268.6,
    "High": 271,
    "Low": 259.4,
    "Vol.": "81.45K",
    "Change %": "-1.16%"
  },
  {
    "Date": "Mar 22, 2015",
    "Price": 268.6,
    "Open": 259.7,
    "High": 270.4,
    "Low": 259,
    "Vol.": "56.63K",
    "Change %": "3.41%"
  },
  {
    "Date": "Mar 21, 2015",
    "Price": 259.7,
    "Open": 261.8,
    "High": 263.3,
    "Low": 254,
    "Vol.": "51.65K",
    "Change %": "-0.79%"
  },
  {
    "Date": "Mar 20, 2015",
    "Price": 261.8,
    "Open": 260.9,
    "High": 264.7,
    "Low": 257.9,
    "Vol.": "52.83K",
    "Change %": "0.33%"
  },
  {
    "Date": "Mar 19, 2015",
    "Price": 260.9,
    "Open": 255.9,
    "High": 264.8,
    "Low": 247,
    "Vol.": "180.69K",
    "Change %": "1.96%"
  },
  {
    "Date": "Mar 18, 2015",
    "Price": 255.9,
    "Open": 285.4,
    "High": 285.6,
    "Low": 248.2,
    "Vol.": "206.74K",
    "Change %": "-10.32%"
  },
  {
    "Date": "Mar 17, 2015",
    "Price": 285.4,
    "Open": 290.4,
    "High": 292.5,
    "Low": 283.3,
    "Vol.": "65.01K",
    "Change %": "-1.73%"
  },
  {
    "Date": "Mar 16, 2015",
    "Price": 290.4,
    "Open": 284.9,
    "High": 294,
    "Low": 284.8,
    "Vol.": "66.34K",
    "Change %": "1.94%"
  },
  {
    "Date": "Mar 15, 2015",
    "Price": 284.9,
    "Open": 281.6,
    "High": 286.4,
    "Low": 280.4,
    "Vol.": "39.46K",
    "Change %": "1.16%"
  },
  {
    "Date": "Mar 14, 2015",
    "Price": 281.6,
    "Open": 287.2,
    "High": 288.4,
    "Low": 279.3,
    "Vol.": "75.72K",
    "Change %": "-1.95%"
  },
  {
    "Date": "Mar 13, 2015",
    "Price": 287.2,
    "Open": 293.9,
    "High": 294.9,
    "Low": 286.1,
    "Vol.": "97.34K",
    "Change %": "-2.26%"
  },
  {
    "Date": "Mar 12, 2015",
    "Price": 293.9,
    "Open": 295.6,
    "High": 297,
    "Low": 290.8,
    "Vol.": "107.32K",
    "Change %": "-0.59%"
  },
  {
    "Date": "Mar 11, 2015",
    "Price": 295.6,
    "Open": 291.4,
    "High": 297.7,
    "Low": 288.9,
    "Vol.": "79.98K",
    "Change %": "1.45%"
  },
  {
    "Date": "Mar 10, 2015",
    "Price": 291.4,
    "Open": 290,
    "High": 301,
    "Low": 288.1,
    "Vol.": "158.18K",
    "Change %": "0.47%"
  },
  {
    "Date": "Mar 09, 2015",
    "Price": 290,
    "Open": 274.5,
    "High": 293.3,
    "Low": 273.8,
    "Vol.": "151.77K",
    "Change %": "5.66%"
  },
  {
    "Date": "Mar 08, 2015",
    "Price": 274.5,
    "Open": 274.9,
    "High": 278.8,
    "Low": 271.3,
    "Vol.": "50.40K",
    "Change %": "-0.15%"
  },
  {
    "Date": "Mar 07, 2015",
    "Price": 274.9,
    "Open": 272.6,
    "High": 278.3,
    "Low": 269.4,
    "Vol.": "60.72K",
    "Change %": "0.86%"
  },
  {
    "Date": "Mar 06, 2015",
    "Price": 272.6,
    "Open": 275.2,
    "High": 278,
    "Low": 269,
    "Vol.": "98.80K",
    "Change %": "-0.97%"
  },
  {
    "Date": "Mar 05, 2015",
    "Price": 275.2,
    "Open": 271.9,
    "High": 280.8,
    "Low": 262.8,
    "Vol.": "123.64K",
    "Change %": "1.22%"
  },
  {
    "Date": "Mar 04, 2015",
    "Price": 271.9,
    "Open": 280.6,
    "High": 284.5,
    "Low": 265.9,
    "Vol.": "139.00K",
    "Change %": "-3.11%"
  },
  {
    "Date": "Mar 03, 2015",
    "Price": 280.6,
    "Open": 273.8,
    "High": 287.1,
    "Low": 266.1,
    "Vol.": "164.82K",
    "Change %": "2.52%"
  },
  {
    "Date": "Mar 02, 2015",
    "Price": 273.8,
    "Open": 257.9,
    "High": 274.8,
    "Low": 256.1,
    "Vol.": "81.09K",
    "Change %": "6.13%"
  },
  {
    "Date": "Mar 01, 2015",
    "Price": 257.9,
    "Open": 254.1,
    "High": 260.6,
    "Low": 244.8,
    "Vol.": "51.33K",
    "Change %": "1.53%"
  },
  {
    "Date": "Feb 28, 2015",
    "Price": 254.1,
    "Open": 253.5,
    "High": 255.4,
    "Low": 248.7,
    "Vol.": "39.41K",
    "Change %": "0.23%"
  },
  {
    "Date": "Feb 27, 2015",
    "Price": 253.5,
    "Open": 236.5,
    "High": 258.7,
    "Low": 235.7,
    "Vol.": "167.81K",
    "Change %": "7.16%"
  },
  {
    "Date": "Feb 26, 2015",
    "Price": 236.5,
    "Open": 237.3,
    "High": 238.2,
    "Low": 233.5,
    "Vol.": "50.87K",
    "Change %": "-0.34%"
  },
  {
    "Date": "Feb 25, 2015",
    "Price": 237.3,
    "Open": 238.9,
    "High": 239.6,
    "Low": 234.6,
    "Vol.": "38.10K",
    "Change %": "-0.65%"
  },
  {
    "Date": "Feb 24, 2015",
    "Price": 238.9,
    "Open": 238.8,
    "High": 240.3,
    "Low": 235.5,
    "Vol.": "45.03K",
    "Change %": "0.03%"
  },
  {
    "Date": "Feb 23, 2015",
    "Price": 238.8,
    "Open": 235.7,
    "High": 240.1,
    "Low": 231.3,
    "Vol.": "62.67K",
    "Change %": "1.31%"
  },
  {
    "Date": "Feb 22, 2015",
    "Price": 235.7,
    "Open": 244.4,
    "High": 246.5,
    "Low": 232.7,
    "Vol.": "75.70K",
    "Change %": "-3.55%"
  },
  {
    "Date": "Feb 21, 2015",
    "Price": 244.4,
    "Open": 244.5,
    "High": 247.3,
    "Low": 242.6,
    "Vol.": "42.95K",
    "Change %": "-0.04%"
  },
  {
    "Date": "Feb 20, 2015",
    "Price": 244.5,
    "Open": 241.9,
    "High": 247.8,
    "Low": 238.8,
    "Vol.": "83.59K",
    "Change %": "1.07%"
  },
  {
    "Date": "Feb 19, 2015",
    "Price": 241.9,
    "Open": 235.2,
    "High": 244.1,
    "Low": 234.9,
    "Vol.": "66.05K",
    "Change %": "2.86%"
  },
  {
    "Date": "Feb 18, 2015",
    "Price": 235.2,
    "Open": 243.2,
    "High": 245.5,
    "Low": 231.7,
    "Vol.": "99.66K",
    "Change %": "-3.29%"
  },
  {
    "Date": "Feb 17, 2015",
    "Price": 243.2,
    "Open": 235.8,
    "High": 247.2,
    "Low": 232,
    "Vol.": "116.26K",
    "Change %": "3.13%"
  },
  {
    "Date": "Feb 16, 2015",
    "Price": 235.8,
    "Open": 233.3,
    "High": 240,
    "Low": 228,
    "Vol.": "115.47K",
    "Change %": "1.10%"
  },
  {
    "Date": "Feb 15, 2015",
    "Price": 233.3,
    "Open": 258.6,
    "High": 264.6,
    "Low": 226.6,
    "Vol.": "179.14K",
    "Change %": "-9.81%"
  },
  {
    "Date": "Feb 14, 2015",
    "Price": 258.6,
    "Open": 236.2,
    "High": 261.3,
    "Low": 235.4,
    "Vol.": "133.80K",
    "Change %": "9.51%"
  },
  {
    "Date": "Feb 13, 2015",
    "Price": 236.2,
    "Open": 221.8,
    "High": 241.6,
    "Low": 220.6,
    "Vol.": "112.25K",
    "Change %": "6.48%"
  },
  {
    "Date": "Feb 12, 2015",
    "Price": 221.8,
    "Open": 218.8,
    "High": 223,
    "Low": 217.3,
    "Vol.": "50.11K",
    "Change %": "1.35%"
  },
  {
    "Date": "Feb 11, 2015",
    "Price": 218.8,
    "Open": 219.7,
    "High": 223.5,
    "Low": 217.3,
    "Vol.": "71.73K",
    "Change %": "-0.38%"
  },
  {
    "Date": "Feb 10, 2015",
    "Price": 219.7,
    "Open": 220.3,
    "High": 222.2,
    "Low": 214.4,
    "Vol.": "86.15K",
    "Change %": "-0.30%"
  },
  {
    "Date": "Feb 09, 2015",
    "Price": 220.3,
    "Open": 223.7,
    "High": 225,
    "Low": 215.7,
    "Vol.": "91.69K",
    "Change %": "-1.49%"
  },
  {
    "Date": "Feb 08, 2015",
    "Price": 223.7,
    "Open": 227.7,
    "High": 230.2,
    "Low": 219.5,
    "Vol.": "29.05K",
    "Change %": "-1.76%"
  },
  {
    "Date": "Feb 07, 2015",
    "Price": 227.7,
    "Open": 223,
    "High": 231,
    "Low": 222.4,
    "Vol.": "39.76K",
    "Change %": "2.12%"
  },
  {
    "Date": "Feb 06, 2015",
    "Price": 223,
    "Open": 216.5,
    "High": 226.2,
    "Low": 215.6,
    "Vol.": "52.52K",
    "Change %": "2.97%"
  },
  {
    "Date": "Feb 05, 2015",
    "Price": 216.5,
    "Open": 226.6,
    "High": 229.9,
    "Low": 214.4,
    "Vol.": "40.64K",
    "Change %": "-4.44%"
  },
  {
    "Date": "Feb 04, 2015",
    "Price": 226.6,
    "Open": 227.4,
    "High": 230.7,
    "Low": 220.2,
    "Vol.": "55.24K",
    "Change %": "-0.36%"
  },
  {
    "Date": "Feb 03, 2015",
    "Price": 227.4,
    "Open": 238.9,
    "High": 247.5,
    "Low": 223.9,
    "Vol.": "63.08K",
    "Change %": "-4.79%"
  },
  {
    "Date": "Feb 02, 2015",
    "Price": 238.9,
    "Open": 225.3,
    "High": 242.5,
    "Low": 220.5,
    "Vol.": "39.02K",
    "Change %": "6.02%"
  },
  {
    "Date": "Feb 01, 2015",
    "Price": 225.3,
    "Open": 218.5,
    "High": 231.4,
    "Low": 209.7,
    "Vol.": "41.16K",
    "Change %": "3.10%"
  },
  {
    "Date": "Jan 31, 2015",
    "Price": 218.5,
    "Open": 231.8,
    "High": 235.4,
    "Low": 216.5,
    "Vol.": "42.15K",
    "Change %": "-5.75%"
  },
  {
    "Date": "Jan 30, 2015",
    "Price": 231.8,
    "Open": 234,
    "High": 244.8,
    "Low": 227.2,
    "Vol.": "48.23K",
    "Change %": "-0.92%"
  },
  {
    "Date": "Jan 29, 2015",
    "Price": 234,
    "Open": 236.2,
    "High": 241.5,
    "Low": 220.4,
    "Vol.": "54.49K",
    "Change %": "-0.92%"
  },
  {
    "Date": "Jan 28, 2015",
    "Price": 236.2,
    "Open": 263.3,
    "High": 267.7,
    "Low": 228.1,
    "Vol.": "63.77K",
    "Change %": "-10.29%"
  },
  {
    "Date": "Jan 27, 2015",
    "Price": 263.3,
    "Open": 269.2,
    "High": 276.9,
    "Low": 247.3,
    "Vol.": "50.26K",
    "Change %": "-2.20%"
  },
  {
    "Date": "Jan 26, 2015",
    "Price": 269.2,
    "Open": 252.1,
    "High": 310.9,
    "Low": 251.5,
    "Vol.": "105.71K",
    "Change %": "6.78%"
  },
  {
    "Date": "Jan 25, 2015",
    "Price": 252.1,
    "Open": 248.2,
    "High": 256.4,
    "Low": 241.4,
    "Vol.": "50.19K",
    "Change %": "1.58%"
  },
  {
    "Date": "Jan 24, 2015",
    "Price": 248.2,
    "Open": 232.2,
    "High": 248.9,
    "Low": 229.6,
    "Vol.": "33.24K",
    "Change %": "6.89%"
  },
  {
    "Date": "Jan 23, 2015",
    "Price": 232.2,
    "Open": 232.7,
    "High": 237,
    "Low": 224.8,
    "Vol.": "38.17K",
    "Change %": "-0.23%"
  },
  {
    "Date": "Jan 22, 2015",
    "Price": 232.7,
    "Open": 228.2,
    "High": 238.8,
    "Low": 225.6,
    "Vol.": "53.71K",
    "Change %": "1.99%"
  },
  {
    "Date": "Jan 21, 2015",
    "Price": 228.2,
    "Open": 210.6,
    "High": 229.3,
    "Low": 207.1,
    "Vol.": "43.18K",
    "Change %": "8.37%"
  },
  {
    "Date": "Jan 20, 2015",
    "Price": 210.6,
    "Open": 215.9,
    "High": 216.6,
    "Low": 203.4,
    "Vol.": "37.48K",
    "Change %": "-2.46%"
  },
  {
    "Date": "Jan 19, 2015",
    "Price": 215.9,
    "Open": 210.6,
    "High": 219.5,
    "Low": 205.5,
    "Vol.": "31.58K",
    "Change %": "2.49%"
  },
  {
    "Date": "Jan 18, 2015",
    "Price": 210.6,
    "Open": 199.6,
    "High": 220.7,
    "Low": 192.5,
    "Vol.": "40.37K",
    "Change %": "5.49%"
  },
  {
    "Date": "Jan 17, 2015",
    "Price": 199.6,
    "Open": 206.9,
    "High": 212.6,
    "Low": 191.7,
    "Vol.": "43.13K",
    "Change %": "-3.51%"
  },
  {
    "Date": "Jan 16, 2015",
    "Price": 206.9,
    "Open": 209.8,
    "High": 222.6,
    "Low": 198.7,
    "Vol.": "62.32K",
    "Change %": "-1.36%"
  },
  {
    "Date": "Jan 15, 2015",
    "Price": 209.8,
    "Open": 164.9,
    "High": 231.3,
    "Low": 164.6,
    "Vol.": "124.67K",
    "Change %": "27.20%"
  },
  {
    "Date": "Jan 14, 2015",
    "Price": 164.9,
    "Open": 221.3,
    "High": 230.9,
    "Low": 157.3,
    "Vol.": "170.68K",
    "Change %": "-25.47%"
  },
  {
    "Date": "Jan 13, 2015",
    "Price": 221.3,
    "Open": 269.3,
    "High": 269.1,
    "Low": 217.1,
    "Vol.": "95.50K",
    "Change %": "-17.84%"
  },
  {
    "Date": "Jan 12, 2015",
    "Price": 269.3,
    "Open": 264.8,
    "High": 273.1,
    "Low": 263.3,
    "Vol.": "25.39K",
    "Change %": "1.72%"
  },
  {
    "Date": "Jan 11, 2015",
    "Price": 264.8,
    "Open": 273.4,
    "High": 278,
    "Low": 263.8,
    "Vol.": "15.11K",
    "Change %": "-3.14%"
  },
  {
    "Date": "Jan 10, 2015",
    "Price": 273.4,
    "Open": 288,
    "High": 289.3,
    "Low": 272,
    "Vol.": "14.73K",
    "Change %": "-5.08%"
  },
  {
    "Date": "Jan 09, 2015",
    "Price": 288,
    "Open": 282.7,
    "High": 290.6,
    "Low": 277.3,
    "Vol.": "20.93K",
    "Change %": "1.87%"
  },
  {
    "Date": "Jan 08, 2015",
    "Price": 282.7,
    "Open": 291.3,
    "High": 292.7,
    "Low": 279,
    "Vol.": "20.18K",
    "Change %": "-2.97%"
  },
  {
    "Date": "Jan 07, 2015",
    "Price": 291.3,
    "Open": 282.3,
    "High": 296.1,
    "Low": 280.7,
    "Vol.": "30.67K",
    "Change %": "3.21%"
  },
  {
    "Date": "Jan 06, 2015",
    "Price": 282.3,
    "Open": 274.8,
    "High": 285.1,
    "Low": 271.5,
    "Vol.": "21.94K",
    "Change %": "2.70%"
  },
  {
    "Date": "Jan 05, 2015",
    "Price": 274.8,
    "Open": 264.7,
    "High": 278.3,
    "Low": 262.9,
    "Vol.": "54.99K",
    "Change %": "3.82%"
  },
  {
    "Date": "Jan 04, 2015",
    "Price": 264.7,
    "Open": 287.1,
    "High": 289.9,
    "Low": 255.9,
    "Vol.": "88.77K",
    "Change %": "-7.80%"
  },
  {
    "Date": "Jan 03, 2015",
    "Price": 287.1,
    "Open": 315.2,
    "High": 315.8,
    "Low": 284.9,
    "Vol.": "47.37K",
    "Change %": "-8.91%"
  },
  {
    "Date": "Jan 02, 2015",
    "Price": 315.2,
    "Open": 314.9,
    "High": 316.4,
    "Low": 313.1,
    "Vol.": "14.73K",
    "Change %": "0.10%"
  },
  {
    "Date": "Jan 01, 2015",
    "Price": 314.9,
    "Open": 318.2,
    "High": 321.4,
    "Low": 313.5,
    "Vol.": "12.82K",
    "Change %": "-1.05%"
  }
]
